vembed/__init__.py
vembed/model/__init__.py
vembed/model/transformer_model.py
vembed/similarity/__init__.py
vembed/similarity/get_similarity.py
vembed/string_to_vector/__init__.py
vembed/string_to_vector/mpnet_paraphrase.py
vembed-0.242.dist-info/LICENSE
vembed-0.242.dist-info/METADATA
vembed-0.242.dist-info/WHEEL
vembed-0.242.dist-info/top_level.txt
vembed-0.242.dist-info/RECORD
