Metadata-Version: 2.1
Name: vembed
Version: 0.242
Summary: Package providing methods to create Vector Embeddings from Strings, calculate similarities between lists of Strings, and Generate Visualizations such as Heatmaps from simple Lists.
Home-page: https://github.com/kuro337/vembed
Author: kuro337
Classifier: Programming Language :: Python :: 3
Classifier: License :: OSI Approved :: MIT License
Classifier: Operating System :: OS Independent
Requires-Python: >=3.5
License-File: LICENSE
Requires-Dist: sentence-transformers
Requires-Dist: torch
Requires-Dist: transformers
Requires-Dist: pandas
Requires-Dist: matplotlib
Requires-Dist: seaborn
